stellarstation/__init__.py
stellarstation/api/__init__.py
stellarstation/api/v1/__init__.py
stellarstation/api/v1/stellarstation_pb2.py
stellarstation/api/v1/stellarstation_pb2_grpc.py
stellarstation/api/v1/transport_pb2.py
stellarstation/api/v1/transport_pb2_grpc.py
stellarstation/api/v1/antenna/__init__.py
stellarstation/api/v1/antenna/antenna_pb2.py
stellarstation/api/v1/antenna/antenna_pb2_grpc.py
stellarstation/api/v1/common/__init__.py
stellarstation/api/v1/common/common_pb2.py
stellarstation/api/v1/common/common_pb2_grpc.py
stellarstation/api/v1/groundstation/__init__.py
stellarstation/api/v1/groundstation/groundstation_pb2.py
stellarstation/api/v1/groundstation/groundstation_pb2_grpc.py
stellarstation/api/v1/monitoring/__init__.py
stellarstation/api/v1/monitoring/monitoring_pb2.py
stellarstation/api/v1/monitoring/monitoring_pb2_grpc.py
stellarstation/api/v1/orbit/__init__.py
stellarstation/api/v1/orbit/orbit_pb2.py
stellarstation/api/v1/orbit/orbit_pb2_grpc.py
stellarstation/api/v1/radio/__init__.py
stellarstation/api/v1/radio/radio_pb2.py
stellarstation/api/v1/radio/radio_pb2_grpc.py
stellarstation-0.15.0.dist-info/LICENSE
stellarstation-0.15.0.dist-info/METADATA
stellarstation-0.15.0.dist-info/WHEEL
stellarstation-0.15.0.dist-info/top_level.txt
stellarstation-0.15.0.dist-info/RECORD
