Metadata-Version: 2.1
Name: stellarstation
Version: 0.15.0
Summary: Client stubs for accessing the StellarStation API
Home-page: https://github.com/infostellarinc/stellarstation-api
Author: StellarStation API Team
Author-email: stellarstation-api-team@istellar.jp
License: UNKNOWN
Platform: UNKNOWN
Classifier: Programming Language :: Python :: 2
Classifier: Programming Language :: Python :: 3
Classifier: License :: OSI Approved :: Apache Software License
Classifier: Operating System :: OS Independent 
Requires-Dist: grpcio
Requires-Dist: protobuf
